setup.py
supervisor_wildcards.egg-info/PKG-INFO
supervisor_wildcards.egg-info/SOURCES.txt
supervisor_wildcards.egg-info/dependency_links.txt
supervisor_wildcards.egg-info/top_level.txt
supervisorwildcards/__init__.py
supervisorwildcards/controllerplugin.py