Metadata-Version: 1.1
Name: supervisor-wildcards
Version: 0.1.3
Summary: Implemenents start/stop/restart commands with both parallel and wildcard support for Supervisor.
Home-page: http://github.com/aleszoulek/supervisor-wildcards
Author: Ales Zoulek
Author-email: ales.zoulek@gmail.com
License: BSD
Platform: UNKNOWN
Classifier: Development Status :: 4 - Beta
Classifier: Programming Language :: Python
Classifier: Programming Language :: Python :: 2
Classifier: Intended Audience :: Developers
Classifier: License :: OSI Approved :: BSD License
